<Properties StartupConfiguration="{EB1DE711-FF18-CBA0-A64A-07334A376EF5}|">
  <MonoDevelop.Ide.Workbench ActiveDocument="Assets/ScriptableObjects/DialogueScriptableObject.cs">
    <Files>
      <File FileName="Assets/Scripts/Player.cs" Line="265" Column="10" />
      <File FileName="Assets/Scripts/MusicManager.cs" />
      <File FileName="Assets/Scripts/EnemyMovement.cs" />
      <File FileName="Assets/Scripts/StartButtonBehavior.cs" />
      <File FileName="Assets/Scripts/OmbreArt.cs" />
      <File FileName="Assets/Scripts/GameController.cs" />
      <File FileName="Assets/Scripts/Dialogue.cs" Line="13" Column="46" />
      <File FileName="Assets/ScriptableObjects/DialogueScriptableObject.cs" Line="15" Column="39" />
    </Files>
  </MonoDevelop.Ide.Workbench>
  <MonoDevelop.Ide.DebuggingService.PinnedWatches />
  <MonoDevelop.Ide.Workspace ActiveConfiguration="Debug" />
  <MonoDevelop.Ide.ItemProperties.Assembly-CSharp PreferredExecutionTarget="fc2bf7f3-673f-47bd-b644-d738807dff79" />
  <MonoDevelop.Ide.DebuggingService.Breakpoints>
    <BreakpointStore />
  </MonoDevelop.Ide.DebuggingService.Breakpoints>
  <MultiItemStartupConfigurations />
</Properties>